{
   "info": {
      "Group": "A-2L-A",
      "Filename": "05-07-2023, 18-48",
      "Runtime": 14400,
      "ModelType": "Basic model with minimum spread",
      "CurrentTime": "2023-05-07 18:48:44"
   },
   "parameters": {
      "AllowedWaitingTime": 7,
      "MinimumCharterPeriod": 60,
      "MinimumDaysBetweenDelivery": 4,
      "ProductionScaleRate": 0.3,
      "CharterOutFrictionRate": 0.05,
      "DesHasLoadingPort": true
   },
   "vars": {
      "x": {
         "x[AD-1,ART_PORT,0,EXIT_PORT,124]": 1.0,
         "x[AD-2,ART_PORT,0,DESCON_3,1]": 1.0,
         "x[AD-2,DESCON_5,50,AD-2-M,122]": 1.0,
         "x[AD-2,AD-2-M,122,EXIT_PORT,124]": 1.0,
         "x[AD-2,DESCON_3,1,FU,24]": 1.0,
         "x[AD-2,FU,24,DESCON_5,50]": 1.0,
         "x[AD-3,ART_PORT,0,DESCON_1,1]": 1.0,
         "x[AD-3,DESCON_1,1,FU,11]": 1.0,
         "x[AD-3,FU,11,DESCON_6,30]": 1.0,
         "x[AD-3,DESCON_6,30,DI,59]": 1.0,
         "x[AD-3,DI,59,DESCON_1,71]": 1.0,
         "x[AD-3,DESCON_1,71,DI,83]": 1.0,
         "x[AD-3,DI,83,DESCON_1,92]": 1.0,
         "x[AD-3,DESCON_2,118,EXIT_PORT,124]": 1.0,
         "x[AD-3,DESCON_1,92,DI,100]": 1.0,
         "x[AD-3,DI,100,DESCON_2,118]": 1.0,
         "x[AD-4,ART_PORT,0,AD-4-start,1]": 1.0,
         "x[AD-4,AD-4-start,1,DI,15]": 1.0,
         "x[AD-4,DESCON_1,25,EXIT_PORT,124]": 1.0,
         "x[AD-4,DI,15,DESCON_1,25]": 1.0,
         "x[AD-5,ART_PORT,0,DESCON_1,1]": 1.0,
         "x[AD-5,DESCON_1,1,DI,11]": 1.0,
         "x[AD-5,DESCON_2,35,EXIT_PORT,124]": 1.0,
         "x[AD-5,DI,11,DESCON_2,35]": 1.0,
         "x[AD-6,ART_PORT,0,EXIT_PORT,124]": 1.0,
         "x[AD-7,ART_PORT,0,EXIT_PORT,124]": 1.0,
         "x[AD-8,ART_PORT,0,DESCON_4,1]": 1.0,
         "x[AD-8,DESCON_4,1,DI,21]": 1.0,
         "x[AD-8,DESCON_1,31,EXIT_PORT,124]": 1.0,
         "x[AD-8,DI,21,DESCON_1,31]": 1.0,
         "x[AD-9,ART_PORT,0,DESCON_2,1]": 1.0,
         "x[AD-9,DESCON_2,1,FU,32]": 1.0,
         "x[AD-9,FU,32,DESCON_6,56]": 1.0,
         "x[AD-9,DESCON_6,56,DI,80]": 1.0,
         "x[AD-9,DESCON_2,104,EXIT_PORT,124]": 1.0,
         "x[AD-9,DI,80,DESCON_2,104]": 1.0,
         "x[AD-10,ART_PORT,0,EXIT_PORT,124]": 1.0,
         "x[AD-11,ART_PORT,0,DESCON_1,1]": 1.0,
         "x[AD-11,DESCON_1,1,FU,12]": 1.0,
         "x[AD-11,FU,12,DESCON_5,30]": 1.0,
         "x[AD-11,DESCON_5,30,DI,53]": 1.0,
         "x[AD-11,DI,53,DESCON_2,73]": 1.0,
         "x[AD-11,DESCON_2,73,DI,89]": 1.0,
         "x[AD-11,DI,89,DESCON_1,96]": 1.0,
         "x[AD-11,DESCON_5,122,EXIT_PORT,124]": 1.0,
         "x[AD-11,DESCON_1,96,FU,104]": 1.0,
         "x[AD-11,FU,104,DESCON_5,122]": 1.0,
         "x[AD-12,ART_PORT,0,EXIT_PORT,124]": 1.0,
         "x[AD-13,ART_PORT,0,DESCON_6,31]": 1.0,
         "x[AD-13,DESCON_6,31,FU,55]": 1.0,
         "x[AD-13,FU,55,DESCON_6,79]": 1.0,
         "x[AD-13,DESCON_6,79,FU,107]": 1.0,
         "x[AD-13,DESCON_6,122,EXIT_PORT,124]": 1.0,
         "x[AD-13,FU,107,DESCON_6,122]": 1.0,
         "x[AD-14,ART_PORT,0,EXIT_PORT,124]": 1.0,
         "x[AD-15,ART_PORT,0,DESCON_1,40]": 1.0,
         "x[AD-15,DESCON_1,40,FU,51]": 1.0,
         "x[AD-15,DESCON_6,75,EXIT_PORT,124]": 1.0,
         "x[AD-15,FU,51,DESCON_6,75]": 1.0
      },
      "s": {
         "s[FU,1]": 106000.0,
         "s[FU,2]": 162000.0,
         "s[FU,3]": 58000.0,
         "s[FU,4]": 114000.0,
         "s[FU,5]": 170000.0,
         "s[FU,6]": 226000.0,
         "s[FU,7]": 282000.0,
         "s[FU,8]": 186626.83523654187,
         "s[FU,9]": 242626.83523654187,
         "s[FU,10]": 298626.83523654187,
         "s[FU,11]": 217126.83523654187,
         "s[FU,12]": 105126.83523654187,
         "s[FU,13]": 161126.83523654187,
         "s[FU,14]": 217126.83523654187,
         "s[FU,15]": 123126.83523654187,
         "s[FU,16]": 179126.83523654187,
         "s[FU,17]": 85126.83523654187,
         "s[FU,18]": 141126.83523654187,
         "s[FU,19]": 197126.83523654187,
         "s[FU,20]": 253126.83523654187,
         "s[FU,21]": 149126.83523654187,
         "s[FU,22]": 205126.83523654187,
         "s[FU,23]": 261126.83523654187,
         "s[FU,24]": 180126.8352365419,
         "s[FU,25]": 86126.83523654191,
         "s[FU,26]": 142126.8352365419,
         "s[FU,27]": 198126.8352365419,
         "s[FU,28]": 94126.83523654191,
         "s[FU,29]": 150126.83523654193,
         "s[FU,30]": 206126.83523654193,
         "s[FU,31]": 262126.83523654193,
         "s[FU,32]": 150126.83523654193,
         "s[FU,33]": 206126.83523654193,
         "s[FU,34]": 122126.83523654191,
         "s[FU,35]": 178126.8352365419,
         "s[FU,36]": 234126.8352365419,
         "s[FU,37]": 153000.00000000006,
         "s[FU,38]": 59000.00000000006,
         "s[FU,39]": 115000.00000000007,
         "s[FU,40]": 171000.00000000006,
         "s[FU,41]": 227000.00000000006,
         "s[FU,42]": 123000.00000000006,
         "s[FU,43]": 179000.00000000006,
         "s[FU,44]": 235000.00000000006,
         "s[FU,45]": 291000.00000000006,
         "s[FU,46]": 52000.00000000006,
         "s[FU,47]": 108000.00000000006,
         "s[FU,48]": 164000.00000000006,
         "s[FU,49]": 220000.00000000006,
         "s[FU,50]": 276000.0,
         "s[FU,51]": 162000.0,
         "s[FU,52]": 218000.0,
         "s[FU,53]": 274000.00000000006,
         "s[FU,54]": 180000.00000000006,
         "s[FU,55]": 68000.00000000006,
         "s[FU,56]": 124000.00000000006,
         "s[FU,57]": 180000.00000000006,
         "s[FU,58]": 236000.00000000006,
         "s[FU,59]": 292000.00000000006,
         "s[FU,60]": 198000.00000000006,
         "s[FU,61]": 104000.00000000006,
         "s[FU,62]": 160000.00000000006,
         "s[FU,63]": 216000.00000000006,
         "s[FU,64]": 132000.00000000006,
         "s[FU,65]": 188000.00000000006,
         "s[FU,66]": 244000.00000000006,
         "s[FU,67]": 300000.0,
         "s[FU,68]": 208243.94917303626,
         "s[FU,69]": 124243.94917303626,
         "s[FU,70]": 180243.94917303626,
         "s[FU,71]": 236243.94917303626,
         "s[FU,72]": 157243.94917303626,
         "s[FU,73]": 74283.43771916331,
         "s[FU,74]": 130283.43771916331,
         "s[FU,75]": 49999.999999732754,
         "s[FU,76]": 105999.99999973443,
         "s[FU,77]": 161999.99999972942,
         "s[FU,78]": 217999.99999972942,
         "s[FU,79]": 273999.99999972945,
         "s[FU,80]": 179999.99999972945,
         "s[FU,81]": 235999.99999972945,
         "s[FU,82]": 134606.51471624523,
         "s[FU,83]": 190606.51471624523,
         "s[FU,84]": 246606.51471624523,
         "s[FU,85]": 152606.51471624523,
         "s[FU,86]": 208606.51471624523,
         "s[FU,87]": 264606.51471624523,
         "s[FU,88]": 170606.51471624515,
         "s[FU,89]": 76606.51471624515,
         "s[FU,90]": 132606.51471624515,
         "s[FU,91]": 188606.51471624515,
         "s[FU,92]": 104606.51471624515,
         "s[FU,93]": 160606.51471624515,
         "s[FU,94]": 216606.51471624515,
         "s[FU,95]": 122606.51471624515,
         "s[FU,96]": 178606.51471624515,
         "s[FU,97]": 234606.514716245,
         "s[FU,98]": 130606.514716245,
         "s[FU,99]": 186606.514716245,
         "s[FU,100]": 107606.514716245,
         "s[FU,101]": 163606.514716245,
         "s[FU,102]": 219606.514716245,
         "s[FU,103]": 275606.514716245,
         "s[FU,104]": 163606.51471624544,
         "s[FU,105]": 219606.51471624544,
         "s[FU,106]": 275606.51471624547,
         "s[FU,107]": 163606.51471624544,
         "s[FU,108]": 219606.51471624544,
         "s[FU,109]": 135606.51471624544,
         "s[FU,110]": 191606.51471624544,
         "s[FU,111]": 107606.51471624544,
         "s[FU,112]": 163606.51471624547,
         "s[FU,113]": 219606.51471624547,
         "s[FU,114]": 275606.51471624547,
         "s[FU,115]": 171606.51471624547,
         "s[FU,116]": 67606.51471624544,
         "s[FU,117]": 123606.51471624544,
         "s[FU,118]": 179606.51471624544,
         "s[FU,119]": 75606.51471624544,
         "s[FU,120]": 131606.51471624547,
         "s[FU,121]": 187606.51471624547,
         "s[FU,122]": 243606.51471624547,
         "s[FU,123]": 299606.51471624547,
         "s[DI,1]": 134000.0,
         "s[DI,2]": 167999.99999999872,
         "s[DI,3]": 51999.99999999549,
         "s[DI,4]": 85999.99999999278,
         "s[DI,5]": 119999.99999998954,
         "s[DI,6]": 153999.99999998577,
         "s[DI,7]": 188000.0000000008,
         "s[DI,8]": 65000.00000001822,
         "s[DI,9]": 99000.00000001822,
         "s[DI,10]": 133000.00000001822,
         "s[DI,11]": 31000.00000001822,
         "s[DI,12]": 65000.00000001822,
         "s[DI,13]": 99000.00000001822,
         "s[DI,14]": 133000.00000001822,
         "s[DI,15]": 30000.00000001822,
         "s[DI,16]": 64000.00000001822,
         "s[DI,17]": 98000.00000001822,
         "s[DI,18]": 132000.00000001822,
         "s[DI,19]": 166000.00000001822,
         "s[DI,20]": 200000.00000001822,
         "s[DI,21]": 69000.00000001822,
         "s[DI,22]": 103000.00000001822,
         "s[DI,23]": 137000.00000001822,
         "s[DI,24]": 171000.00000001822,
         "s[DI,25]": 44999.99999998853,
         "s[DI,26]": 78999.99999998853,
         "s[DI,27]": 112999.99999998853,
         "s[DI,28]": 146999.99999998853,
         "s[DI,29]": 180999.99999998853,
         "s[DI,30]": 54999.999999988446,
         "s[DI,31]": 88999.99999998845,
         "s[DI,32]": 122999.99999998846,
         "s[DI,33]": 156999.99999998847,
         "s[DI,34]": 190999.99999998847,
         "s[DI,35]": 79999.99999998847,
         "s[DI,36]": 113999.99999998846,
         "s[DI,37]": 147999.99999998847,
         "s[DI,38]": 181999.99999998847,
         "s[DI,39]": 215999.99999998847,
         "s[DI,40]": 249999.99999998847,
         "s[DI,41]": 133999.99999998847,
         "s[DI,42]": 167999.99999998847,
         "s[DI,43]": 201999.99999998847,
         "s[DI,44]": 78500.00000004892,
         "s[DI,45]": 112500.00000004892,
         "s[DI,46]": 146500.00000004892,
         "s[DI,47]": 180500.00000004892,
         "s[DI,48]": 54500.00000004892,
         "s[DI,49]": 88500.00000004892,
         "s[DI,50]": 122500.00000004892,
         "s[DI,51]": 156500.00000004892,
         "s[DI,52]": 190500.00000004892,
         "s[DI,53]": 56500.00000004892,
         "s[DI,54]": 90500.00000004892,
         "s[DI,55]": 124500.00000004892,
         "s[DI,56]": 158500.00000004892,
         "s[DI,57]": 192500.00000004892,
         "s[DI,58]": 226500.00000004892,
         "s[DI,59]": 123000.00000004892,
         "s[DI,60]": 157000.00000004892,
         "s[DI,61]": 191000.00000004887,
         "s[DI,62]": 80000.00000004887,
         "s[DI,63]": 114000.00000004392,
         "s[DI,64]": 148000.00000004392,
         "s[DI,65]": 182000.00000004392,
         "s[DI,66]": 216000.00000004392,
         "s[DI,67]": 250000.00000004267,
         "s[DI,68]": 139000.00000004267,
         "s[DI,69]": 173000.0000000437,
         "s[DI,70]": 207000.00000004392,
         "s[DI,71]": 241000.00000004558,
         "s[DI,72]": 135623.37662339903,
         "s[DI,73]": 169623.37662339903,
         "s[DI,74]": 61999.99999993527,
         "s[DI,75]": 95999.99999993527,
         "s[DI,76]": 129999.99999993527,
         "s[DI,77]": 163999.99999993527,
         "s[DI,78]": 197999.99999993527,
         "s[DI,79]": 231999.99999993527,
         "s[DI,80]": 97999.99999993571,
         "s[DI,81]": 131999.9999999357,
         "s[DI,82]": 165999.9999999357,
         "s[DI,83]": 62499.99999993571,
         "s[DI,84]": 96499.99999993571,
         "s[DI,85]": 130499.99999993571,
         "s[DI,86]": 164499.9999999357,
         "s[DI,87]": 198499.9999999357,
         "s[DI,88]": 232499.9999999357,
         "s[DI,89]": 98499.99999993571,
         "s[DI,90]": 132499.9999999357,
         "s[DI,91]": 166499.9999999357,
         "s[DI,92]": 40499.99999993571,
         "s[DI,93]": 74499.99999993571,
         "s[DI,94]": 108499.99999993571,
         "s[DI,95]": 142499.9999999357,
         "s[DI,96]": 176499.9999999357,
         "s[DI,97]": 210499.9999999357,
         "s[DI,98]": 244499.9999999357,
         "s[DI,99]": 133499.9999999357,
         "s[DI,100]": 29999.999999939042,
         "s[DI,101]": 63999.99999994071,
         "s[DI,102]": 97999.99999993571,
         "s[DI,103]": 131999.9999999357,
         "s[DI,104]": 165999.9999999357,
         "s[DI,105]": 199999.9999999357,
         "s[DI,106]": 89000.00000002244,
         "s[DI,107]": 123000.00000002244,
         "s[DI,108]": 157000.00000002244,
         "s[DI,109]": 191000.00000002244,
         "s[DI,110]": 80000.00000002244,
         "s[DI,111]": 114000.00000002244,
         "s[DI,112]": 148000.00000002244,
         "s[DI,113]": 182000.00000002244,
         "s[DI,114]": 216000.00000002244,
         "s[DI,115]": 250000.00000001912,
         "s[DI,116]": 131000.0000000223,
         "s[DI,117]": 29999.99999999949,
         "s[DI,118]": 63999.99999999872,
         "s[DI,119]": 97999.99999999741,
         "s[DI,120]": 131999.99999999616,
         "s[DI,121]": 165999.99999999616,
         "s[DI,122]": 199999.99999999616,
         "s[DI,123]": 233999.99999999616
      },
      "g": {
         "g[FU,3,DESCON_6]": 160000.0,
         "g[FU,8,DESCON_2]": 151373.16476345813,
         "g[FU,21,DESCON_3]": 160000.0,
         "g[FU,26,DESCON_5]": 1.4551915228366852e-11,
         "g[FU,28,DESCON_6]": 160000.0,
         "g[FU,37,DESCON_5]": 137126.83523654184,
         "g[FU,40,DESCON_4]": 1.4551915228366852e-11,
         "g[FU,42,DESCON_4]": 160000.0,
         "g[FU,46,DESCON_4]": 135000.0,
         "g[FU,46,DESCON_5]": 160000.0,
         "g[FU,67,DESCON_4]": 5.820766091346741e-11,
         "g[FU,68,DESCON_1]": 147756.05082696374,
         "g[FU,72,DESCON_1]": 135000.0,
         "g[FU,73,DESCON_4]": 138960.51145387295,
         "g[FU,75,DESCON_2]": 136283.4377194339,
         "g[FU,82,DESCON_4]": 157393.48528348422,
         "g[FU,97,DESCON_5]": 1.4551915228366852e-10,
         "g[FU,98,DESCON_6]": 160000.0,
         "g[FU,100,DESCON_5]": 135000.0,
         "g[FU,115,DESCON_2]": 160000.0,
         "g[FU,116,DESCON_6]": 160000.0,
         "g[FU,119,DESCON_3]": 160000.0,
         "g[DI,8,DESCON_1]": 156999.99999998257,
         "g[DI,25,DESCON_6]": 160000.00000002843,
         "g[DI,30,DESCON_2]": 160000.0,
         "g[DI,44,DESCON_2]": 157499.99999993955,
         "g[DI,48,DESCON_6]": 160000.0,
         "g[DI,72,DESCON_2]": 139376.6233766499,
         "g[DI,74,DESCON_3]": 141623.37662346376,
         "g[DI,92,DESCON_6]": 160000.0,
         "g[DI,106,DESCON_3]": 144999.99999991283,
         "g[DI,116,DESCON_5]": 153000.00000000017,
         "g[DI,117,DESCON_4]": 135000.00000002614
      },
      "z": {
         "z[FOBCON_2-1,17]": 1.0,
         "z[FOBCON_2-2,15]": 1.0,
         "z[FOBCON_2-3,60]": 1.0,
         "z[FOBCON_2-4,61]": 1.0,
         "z[FOBCON_2-5,34]": 1.0,
         "z[FOBCON_2-6,69]": 1.0,
         "z[FOBCON_2-7,64]": 1.0,
         "z[FOBCON_2-8,92]": 1.0,
         "z[FOBCON_2-9,109]": 1.0,
         "z[FOBCON_2-10,111]": 1.0,
         "z[FOBCON_1-1,3]": 1.0,
         "z[FOBCON_1-2,41]": 1.0,
         "z[FOBCON_1-3,35]": 1.0,
         "z[FOBCON_1-4,68]": 1.0,
         "z[FOBCON_1-5,62]": 1.0,
         "z[FOBCON_1-6,99]": 1.0,
         "z[FOBCON_1-7,110]": 1.0,
         "z[ART_FIC_FU,25]": 1.0,
         "z[ART_FIC_FU,38]": 1.0,
         "z[ART_FIC_FU,54]": 1.0,
         "z[ART_FIC_FU,80]": 1.0,
         "z[ART_FIC_FU,85]": 1.0,
         "z[ART_FIC_FU,88]": 1.0,
         "z[ART_FIC_FU,89]": 1.0,
         "z[ART_FIC_FU,95]": 1.0
      },
      "q": {},
      "y": {}
   }
}